odoo/addons/account_check_printing_report_dlt103/README.rst
odoo/addons/account_check_printing_report_dlt103/__init__.py
odoo/addons/account_check_printing_report_dlt103/__manifest__.py
odoo/addons/account_check_printing_report_dlt103/data/account_payment_check_report_data.xml
odoo/addons/account_check_printing_report_dlt103/data/report_paperformat.xml
odoo/addons/account_check_printing_report_dlt103/data/report_paperformat_parameter.xml
odoo/addons/account_check_printing_report_dlt103/report/__init__.py
odoo/addons/account_check_printing_report_dlt103/report/account_check_writing_report.xml
odoo/addons/account_check_printing_report_dlt103/report/check_print.py
odoo/addons/account_check_printing_report_dlt103/views/report_check_dlt103.xml
odoo11_addon_account_check_printing_report_dlt103-11.0.1.0.0.dist-info/DESCRIPTION.rst
odoo11_addon_account_check_printing_report_dlt103-11.0.1.0.0.dist-info/METADATA
odoo11_addon_account_check_printing_report_dlt103-11.0.1.0.0.dist-info/RECORD
odoo11_addon_account_check_printing_report_dlt103-11.0.1.0.0.dist-info/WHEEL
odoo11_addon_account_check_printing_report_dlt103-11.0.1.0.0.dist-info/metadata.json
odoo11_addon_account_check_printing_report_dlt103-11.0.1.0.0.dist-info/top_level.txt
